lncrnapi/model/catboost_dnabert2_esm-t30.joblib
lncrnapi/python_scripts/lncrnapi.py
lncrnapi-1.0.0.dist-info/licenses/LICENSE
lncrnapi-1.0.0.dist-info/METADATA
lncrnapi-1.0.0.dist-info/WHEEL
lncrnapi-1.0.0.dist-info/entry_points.txt
lncrnapi-1.0.0.dist-info/top_level.txt
lncrnapi-1.0.0.dist-info/RECORD
