Metadata-Version: 2.4
Name: lncrnapi
Version: 1.0.0
Summary: A CLI tool for predicting lncRNA–Protein interactions using transformer embeddings and CatBoost
Home-page: https://github.com/raghavagps/lncrnapi
Author: Gajendra P.S. Raghava
Author-email: raghava@iiitd.ac.in
Keywords: lncrna protein interaction prediction bioinformatics catboost transformers
Classifier: Programming Language :: Python :: 3
Classifier: License :: OSI Approved :: GNU General Public License v3 (GPLv3)
Classifier: Operating System :: OS Independent
Classifier: Intended Audience :: Science/Research
Classifier: Topic :: Scientific/Engineering :: Bio-Informatics
Requires-Python: >=3.9
License-File: LICENSE
Requires-Dist: torch>=2.6.0
Requires-Dist: transformers>=4.40.0
Requires-Dist: catboost>=1.2
Requires-Dist: joblib>=1.2
Requires-Dist: tqdm>=4.65
Requires-Dist: numpy>=1.24
Requires-Dist: pandas>=2.0
Requires-Dist: safetensors>=0.6
Dynamic: author
Dynamic: author-email
Dynamic: classifier
Dynamic: description
Dynamic: description-content-type
Dynamic: home-page
Dynamic: keywords
Dynamic: license-file
Dynamic: requires-dist
Dynamic: requires-python
Dynamic: summary
